pyhydrology/ERA5downloader.py
pyhydrology/__init__.py
pyhydrology/config.py
pyhydrology/dem.py
pyhydrology/netcdf.py
pyhydrology/scripts/era5_land_download.py
pyhydrology/scripts/era5_land_download_parallel.py
pyhydrology/scripts/readNC.py
pyhydrology/scripts/read_nc_with_elevation.py
pyhydrology/scripts/ts.py
pyhydrology-0.2.0.dist-info/METADATA
pyhydrology-0.2.0.dist-info/WHEEL
pyhydrology-0.2.0.dist-info/entry_points.txt
pyhydrology-0.2.0.dist-info/licenses/LICENSE
pyhydrology-0.2.0.dist-info/RECORD
