Metadata-Version: 2.4
Name: pyhydrology
Version: 0.2.0
Summary: Tools for hydrology: ERA5 downloader and NetCDF point extractor.
Project-URL: Homepage, https://github.com/SanjeevBashyal/pyhydrology
Project-URL: Source, https://github.com/SanjeevBashyal/pyhydrology
Author-email: Sanjeev Bashyal <sanjeev.bashyal01@gmail.com>
License: MIT
License-File: LICENSE
Keywords: ERA5,cdsapi,hydrology,netcdf,xarray
Classifier: License :: OSI Approved :: MIT License
Classifier: Operating System :: OS Independent
Classifier: Programming Language :: Python :: 3
Requires-Python: >=3.9
Requires-Dist: cdsapi
Requires-Dist: geopandas
Requires-Dist: netcdf4
Requires-Dist: numpy
Requires-Dist: pandas
Requires-Dist: rasterio
Requires-Dist: rioxarray
Requires-Dist: shapely
Requires-Dist: xarray
